RealtimeTTS/__init__.py
RealtimeTTS/stream_player.py
RealtimeTTS/text_to_stream.py
RealtimeTTS/threadsafe_generators.py
RealtimeTTS/engines/__init__.py
RealtimeTTS/engines/azure_engine.py
RealtimeTTS/engines/base_engine.py
RealtimeTTS/engines/chinese.json
RealtimeTTS/engines/coqui_default_voice.json
RealtimeTTS/engines/coqui_engine.py
RealtimeTTS/engines/edge_engine.py
RealtimeTTS/engines/elevenlabs_engine.py
RealtimeTTS/engines/female.json
RealtimeTTS/engines/gtts_engine.py
RealtimeTTS/engines/kokoro_engine.py
RealtimeTTS/engines/male.json
RealtimeTTS/engines/openai_engine.py
RealtimeTTS/engines/orpheus_decoder.py
RealtimeTTS/engines/orpheus_engine.py
RealtimeTTS/engines/parler_engine.py
RealtimeTTS/engines/piper_engine.py
RealtimeTTS/engines/safepipe.py
RealtimeTTS/engines/style_engine.py
RealtimeTTS/engines/system_engine.py
tests/__init__.py
tests/advanced_talk.py
tests/azure_test.py
tests/chinese_test.py
tests/complex_test.py
tests/coqui_test.py
tests/coqui_test_stop.py
tests/edge_test.py
tests/elevenlabs_test.py
tests/fallback_test.py
tests/gtts_test.py
tests/install_packages.py
tests/kokoro_mix_voices.py
tests/kokoro_test.py
tests/minimalistic_talkbot.py
tests/multilang_test_textual.py
tests/multilang_tts_test.py
tests/on_audio_chunk.py
tests/openai_1.0_test.py
tests/openai_test.py
tests/openai_voice_interface.py
tests/openaitts_test.py
tests/orpheus_test.py
tests/parler_test.py
tests/piper_test.py
tests/pyqt6_speed_test.py
tests/pyqt6_speed_test_chinese.py
tests/simple_llm_test.py
tests/simple_test.py
tests/style_test.py
tests/test_callbacks.py
tests/test_on_audio_chunk_callback.py
tests/translator.py
tests/write_to_file.py
realtimetts-0.5.6.dist-info/METADATA
realtimetts-0.5.6.dist-info/WHEEL
realtimetts-0.5.6.dist-info/top_level.txt
realtimetts-0.5.6.dist-info/RECORD
