Metadata-Version: 2.4
Name: realtimetts
Version: 0.5.6
Summary: Stream text into audio with an easy-to-use, highly configurable library delivering voice output with minimal latency.
Home-page: https://github.com/KoljaB/realtimetts
Author: Kolja Beigel
Author-email: kolja.beigel@web.de
Keywords: real-time,text-to-speech,TTS,streaming,audio,voice,synthesis,sentence-segmentation,low-latency,character-streaming,dynamic feedback,audio-output,text-input,TTS-engine,audio-playback,stream-player,sentence-fragment,audio-feedback,interactive,python
Classifier: Programming Language :: Python :: 3
Classifier: License :: OSI Approved :: MIT License
Classifier: Operating System :: OS Independent
Requires-Python: >=3.9, <3.13
Requires-Dist: stream2sentence==0.3.1
Requires-Dist: pydub==0.25.1
Requires-Dist: pyaudio==0.2.14
Requires-Dist: resampy==0.4.3
Provides-Extra: minimal
Requires-Dist: stream2sentence==0.3.1; extra == "minimal"
Requires-Dist: pydub==0.25.1; extra == "minimal"
Requires-Dist: pyaudio==0.2.14; extra == "minimal"
Requires-Dist: resampy==0.4.3; extra == "minimal"
Provides-Extra: all
Requires-Dist: stream2sentence==0.3.1; extra == "all"
Requires-Dist: pydub==0.25.1; extra == "all"
Requires-Dist: pyaudio==0.2.14; extra == "all"
Requires-Dist: resampy==0.4.3; extra == "all"
Requires-Dist: pyttsx3==2.98; extra == "all"
Requires-Dist: azure-cognitiveservices-speech==1.44.0; extra == "all"
Requires-Dist: elevenlabs==2.5.0; extra == "all"
Requires-Dist: openai==1.92.2; extra == "all"
Requires-Dist: gtts==2.5.4; extra == "all"
Requires-Dist: coqui_tts==0.26.2; extra == "all"
Requires-Dist: edge-tts==7.0.2; extra == "all"
Requires-Dist: kokoro==0.9.4; extra == "all"
Provides-Extra: system
Requires-Dist: stream2sentence==0.3.1; extra == "system"
Requires-Dist: pydub==0.25.1; extra == "system"
Requires-Dist: pyaudio==0.2.14; extra == "system"
Requires-Dist: resampy==0.4.3; extra == "system"
Requires-Dist: pyttsx3==2.98; extra == "system"
Provides-Extra: azure
Requires-Dist: stream2sentence==0.3.1; extra == "azure"
Requires-Dist: pydub==0.25.1; extra == "azure"
Requires-Dist: pyaudio==0.2.14; extra == "azure"
Requires-Dist: resampy==0.4.3; extra == "azure"
Requires-Dist: azure-cognitiveservices-speech==1.44.0; extra == "azure"
Provides-Extra: elevenlabs
Requires-Dist: stream2sentence==0.3.1; extra == "elevenlabs"
Requires-Dist: pydub==0.25.1; extra == "elevenlabs"
Requires-Dist: pyaudio==0.2.14; extra == "elevenlabs"
Requires-Dist: resampy==0.4.3; extra == "elevenlabs"
Requires-Dist: elevenlabs==2.5.0; extra == "elevenlabs"
Provides-Extra: openai
Requires-Dist: stream2sentence==0.3.1; extra == "openai"
Requires-Dist: pydub==0.25.1; extra == "openai"
Requires-Dist: pyaudio==0.2.14; extra == "openai"
Requires-Dist: resampy==0.4.3; extra == "openai"
Requires-Dist: openai==1.92.2; extra == "openai"
Provides-Extra: gtts
Requires-Dist: stream2sentence==0.3.1; extra == "gtts"
Requires-Dist: pydub==0.25.1; extra == "gtts"
Requires-Dist: pyaudio==0.2.14; extra == "gtts"
Requires-Dist: resampy==0.4.3; extra == "gtts"
Requires-Dist: gtts==2.5.4; extra == "gtts"
Provides-Extra: coqui
Requires-Dist: stream2sentence==0.3.1; extra == "coqui"
Requires-Dist: pydub==0.25.1; extra == "coqui"
Requires-Dist: pyaudio==0.2.14; extra == "coqui"
Requires-Dist: resampy==0.4.3; extra == "coqui"
Requires-Dist: coqui_tts==0.26.2; extra == "coqui"
Provides-Extra: edge
Requires-Dist: stream2sentence==0.3.1; extra == "edge"
Requires-Dist: pydub==0.25.1; extra == "edge"
Requires-Dist: pyaudio==0.2.14; extra == "edge"
Requires-Dist: resampy==0.4.3; extra == "edge"
Requires-Dist: edge-tts==7.0.2; extra == "edge"
Provides-Extra: kokoro
Requires-Dist: stream2sentence==0.3.1; extra == "kokoro"
Requires-Dist: pydub==0.25.1; extra == "kokoro"
Requires-Dist: pyaudio==0.2.14; extra == "kokoro"
Requires-Dist: resampy==0.4.3; extra == "kokoro"
Requires-Dist: kokoro==0.9.4; extra == "kokoro"
Provides-Extra: orpheus
Requires-Dist: stream2sentence==0.3.1; extra == "orpheus"
Requires-Dist: pydub==0.25.1; extra == "orpheus"
Requires-Dist: pyaudio==0.2.14; extra == "orpheus"
Requires-Dist: resampy==0.4.3; extra == "orpheus"
Requires-Dist: snac==1.2.1; extra == "orpheus"
Provides-Extra: jp
Requires-Dist: stream2sentence==0.3.1; extra == "jp"
Requires-Dist: pydub==0.25.1; extra == "jp"
Requires-Dist: pyaudio==0.2.14; extra == "jp"
Requires-Dist: resampy==0.4.3; extra == "jp"
Requires-Dist: mecab-python3==1.0.6; extra == "jp"
Requires-Dist: unidic-lite==1.0.8; extra == "jp"
Requires-Dist: cutlet; extra == "jp"
Requires-Dist: fugashi==1.4.0; extra == "jp"
Requires-Dist: jaconv==0.4.0; extra == "jp"
Requires-Dist: mojimoji==0.0.13; extra == "jp"
Requires-Dist: pyopenjtalk==0.4.0; extra == "jp"
Provides-Extra: zh
Requires-Dist: stream2sentence==0.3.1; extra == "zh"
Requires-Dist: pydub==0.25.1; extra == "zh"
Requires-Dist: pyaudio==0.2.14; extra == "zh"
Requires-Dist: resampy==0.4.3; extra == "zh"
Requires-Dist: pypinyin==0.53.0; extra == "zh"
Requires-Dist: ordered_set==4.1.0; extra == "zh"
Requires-Dist: jieba==0.42.1; extra == "zh"
Requires-Dist: cn2an==0.5.23; extra == "zh"
Provides-Extra: ko
Requires-Dist: stream2sentence==0.3.1; extra == "ko"
Requires-Dist: pydub==0.25.1; extra == "ko"
Requires-Dist: pyaudio==0.2.14; extra == "ko"
Requires-Dist: resampy==0.4.3; extra == "ko"
Requires-Dist: hangul_romanize; extra == "ko"
Dynamic: author
Dynamic: author-email
Dynamic: classifier
Dynamic: description
Dynamic: description-content-type
Dynamic: home-page
Dynamic: keywords
Dynamic: provides-extra
Dynamic: requires-dist
Dynamic: requires-python
Dynamic: summary
